cast_cli/__init__.py
cast_cli/_cli.py
cast_cli/tests/__init__.py
cast_cli-0.7.1.dist-info/COPYING
cast_cli-0.7.1.dist-info/METADATA
cast_cli-0.7.1.dist-info/WHEEL
cast_cli-0.7.1.dist-info/entry_points.txt
cast_cli-0.7.1.dist-info/top_level.txt
cast_cli-0.7.1.dist-info/RECORD
